latexcalc/__init__.py
latexcalc-0.8.1.dist-info/LICENSE
latexcalc-0.8.1.dist-info/METADATA
latexcalc-0.8.1.dist-info/WHEEL
latexcalc-0.8.1.dist-info/top_level.txt
latexcalc-0.8.1.dist-info/RECORD
