Metadata-Version: 2.1
Name: latexcalc
Version: 0.8.1
Summary: LaTeXcalc is a LaTeX-Calculation-library for python3 accepting an optional values-dict for variables
Home-page: https://github.com/polarwinkel/latexcalc
Author: Dirk Winkel
Author-email: it@polarwinkel.de
Project-URL: Bug Reports, https://github.com/polarwinkel/latexcalc/issues
Project-URL: Source, https://github.com/polarwinkel/latexcalc
Keywords: TeX,LaTeX,latexcalc,texcalc,calctex,calclatex,calculate
Classifier: Development Status :: 4 - Beta
Classifier: Intended Audience :: Developers
Classifier: Intended Audience :: Education
Classifier: License :: OSI Approved :: GNU Affero General Public License v3 or later (AGPLv3+)
Classifier: Programming Language :: Python :: 3
Classifier: Topic :: Scientific/Engineering
Classifier: Topic :: Scientific/Engineering :: Mathematics
Classifier: Topic :: Scientific/Engineering :: Physics
Classifier: Topic :: Software Development
Classifier: Topic :: Software Development :: Libraries
Classifier: Topic :: Software Development :: Libraries :: Python Modules
Classifier: Topic :: Text Processing :: Markup
Classifier: Topic :: Text Processing :: Markup :: LaTeX
Requires-Python: >=3.7, <4
License-File: LICENSE
Requires-Dist: latexcalc
